Metadata-Version: 2.1
Name: textgen
Version: 1.1.1
Summary: Text Generation Model
Home-page: https://github.com/shibing624/textgen
Author: XuMing
Author-email: xuming624@qq.com
License: Apache 2.0
Keywords: textgen,text-generation,Text Generation Tool,ernie-gen,chinese text generation
Platform: UNKNOWN
Classifier: Intended Audience :: Developers
Classifier: Operating System :: OS Independent
Classifier: License :: OSI Approved :: Apache Software License
Classifier: Programming Language :: Python :: 3
Classifier: Topic :: Text Processing :: Linguistic
Classifier: Topic :: Scientific/Engineering :: Artificial Intelligence
Requires-Python: >=3.6
